first_poet_lib/__init__.py
first_poet_lib-0.1.0.dist-info/WHEEL
first_poet_lib-0.1.0.dist-info/METADATA
first_poet_lib-0.1.0.dist-info/RECORD
