Metadata-Version: 2.1
Name: first-poet-lib
Version: 0.1.0
Summary: 
Author: jagadeesh32
Author-email: katla.jagadeesh@gmail.com
Requires-Python: >=3.9,<4.0
Classifier: Programming Language :: Python :: 3
Classifier: Programming Language :: Python :: 3.9
Requires-Dist: requests (==2.20.0)
